{
  "type": "Feature",
  "properties": {
    "gn:admin1_code":"PTF",
    "gn:asciiname":"Hubert's Town",
    "gn:country_code":"TT",
    "gn:dem":34,
    "gn:feature_class":"P",
    "gn:feature_code":"PPL",
    "gn:name":"Hubert\u2019s Town",
    "gn:population":0,
    "gn:timezone":"America/Port_of_Spain",
    "iso:country":"TT",
    "wof:name":"Hubert's Town",
    "wof:placetype":"locality"
},
  "geometry": {"coordinates":[-61.63799,10.17933],"type":"Point"}
}