{
  "type": "Feature",
  "properties": {
    "gn:admin1_code":"TUP",
    "gn:asciiname":"El Dorado",
    "gn:country_code":"TT",
    "gn:dem":15,
    "gn:feature_class":"P",
    "gn:feature_code":"PPL",
    "gn:name":"El Dorado",
    "gn:population":0,
    "gn:timezone":"America/Port_of_Spain",
    "iso:country":"TT",
    "wof:name":"El Dorado",
    "wof:placetype":"locality"
},
  "geometry": {"coordinates":[-61.3805,10.63982],"type":"Point"}
}