{
  "type": "Feature",
  "properties": {
    "gn:admin1_code":"SIP",
    "gn:asciiname":"Bonasse",
    "gn:country_code":"TT",
    "gn:dem":7,
    "gn:feature_class":"P",
    "gn:feature_code":"PPL",
    "gn:name":"Bonasse",
    "gn:population":0,
    "gn:timezone":"America/Port_of_Spain",
    "iso:country":"TT",
    "name:und_x_variant":[
        "Bonasse Village",
        "Bonasse"
    ],
    "wof:name":"Bonasse",
    "wof:placetype":"locality"
},
  "geometry": {"coordinates":[-61.86097,10.09103],"type":"Point"}
}