{
  "type": "Feature",
  "properties": {
    "gn:admin1_code":"TUP",
    "gn:asciiname":"La Pastora",
    "gn:country_code":"TT",
    "gn:dem":429,
    "gn:feature_class":"P",
    "gn:feature_code":"PPL",
    "gn:name":"La Pastora",
    "gn:population":0,
    "gn:timezone":"America/Port_of_Spain",
    "iso:country":"TT",
    "name:und_x_variant":[
        "La Pastoria",
        "La Pastora"
    ],
    "wof:name":"La Pastora",
    "wof:placetype":"locality"
},
  "geometry": {"coordinates":[-61.31613,10.69969],"type":"Point"}
}