{
  "type": "Feature",
  "properties": {
    "gn:admin1_code":"TUP",
    "gn:asciiname":"La Pastora",
    "gn:country_code":"TT",
    "gn:dem":429,
    "gn:feature_class":"P",
    "gn:feature_code":"PPL",
    "gn:name":"La Pastora",
    "gn:population":0,
    "gn:timezone":"America/Port_of_Spain",
    "iso:country":"TT",
    "name:eus_x_preferred":[
        "La Pastora"
    ],
    "name:ita_x_preferred":[
        "La Pastora"
    ],
    "name:por_x_preferred":[
        "La Pastora"
    ],
    "name:spa_x_preferred":[
        "La Pastora"
    ],
    "name:und_x_variant":[
        "La Pastoria",
        "La Pastora"
    ],
    "name:urd_x_preferred":[
        "\u0644\u0627 \u067e\u0627\u0633\u0679\u0648\u0631\u0627"
    ],
    "name:zho_x_preferred":[
        "\u62c9\u5e15\u65af\u6258\u62c9"
    ],
    "wof:name":"La Pastora",
    "wof:placetype":"locality"
},
  "geometry": {"coordinates":[-61.31613,10.69969],"type":"Point"}
}