{
  "type": "Feature",
  "properties": {
    "gn:admin1_code":"CTT",
    "gn:asciiname":"Coryal",
    "gn:country_code":"TT",
    "gn:dem":14,
    "gn:feature_class":"P",
    "gn:feature_code":"PPL",
    "gn:name":"Coryal",
    "gn:population":0,
    "gn:timezone":"America/Port_of_Spain",
    "iso:country":"TT",
    "wof:name":"Coryal",
    "wof:placetype":"locality"
},
  "geometry": {"coordinates":[-61.43425,10.48478],"type":"Point"}
}