{
  "type": "Feature",
  "properties": {
    "gn:admin1_code":"11",
    "gn:asciiname":"Merchiston",
    "gn:country_code":"TT",
    "gn:dem":193,
    "gn:feature_class":"P",
    "gn:feature_code":"PPL",
    "gn:name":"Merchiston",
    "gn:population":0,
    "gn:timezone":"America/Port_of_Spain",
    "iso:country":"TT",
    "name:deu_x_preferred":[
        "Merchiston"
    ],
    "name:eus_x_preferred":[
        "Merchiston"
    ],
    "name:por_x_preferred":[
        "Merchiston"
    ],
    "wof:name":"Merchiston",
    "wof:placetype":"locality"
},
  "geometry": {"coordinates":[-60.53211,11.27446],"type":"Point"}
}