{
  "type": "Feature",
  "properties": {
    "gn:admin1_code":"CTT",
    "gn:asciiname":"Unis",
    "gn:country_code":"TT",
    "gn:dem":72,
    "gn:feature_class":"P",
    "gn:feature_code":"PPL",
    "gn:name":"Unis",
    "gn:population":0,
    "gn:timezone":"America/Port_of_Spain",
    "iso:country":"TT",
    "wof:name":"Unis",
    "wof:placetype":"locality"
},
  "geometry": {"coordinates":[-61.27803,10.3339],"type":"Point"}
}