{
  "type": "Feature",
  "properties": {
    "gn:admin1_code":"10",
    "gn:asciiname":"Saint Joseph",
    "gn:country_code":"TT",
    "gn:dem":20,
    "gn:feature_class":"P",
    "gn:feature_code":"PPL",
    "gn:name":"Saint Joseph",
    "gn:population":0,
    "gn:timezone":"America/Port_of_Spain",
    "iso:country":"TT",
    "name:und_x_variant":[
        "Saint Joseph Village",
        "Saint Joseph"
    ],
    "wof:name":"Saint Joseph",
    "wof:placetype":"locality"
},
  "geometry": {"coordinates":[-61.44696999999999,10.28448],"type":"Point"}
}