{
  "type": "Feature",
  "properties": {
    "iso:country":"TT",
    "name:deu_x_preferred":[
        "La Brea"
    ],
    "name:dut_x_preferred":[
        "La Brea"
    ],
    "name:eng_x_preferred":[
        "La Brea"
    ],
    "name:est_x_preferred":[
        "La Brea"
    ],
    "name:fra_x_preferred":[
        "La Brea"
    ],
    "name:fre_x_preferred":[
        "La Brea"
    ],
    "name:ger_x_preferred":[
        "La Brea"
    ],
    "name:jpn_x_preferred":[
        "\u30e9\u30fb\u30d6\u30ec\u30a2"
    ],
    "name:pol_x_preferred":[
        "La Brea"
    ],
    "name:spa_x_preferred":[
        "La Brea"
    ],
    "name:unk_x_variant":[
        "La Brea Village"
    ],
    "name:urd_x_preferred":[
        "\u0644\u0627 \u0628\u0631\u06cc\u0627\u060c \u0679\u0631\u06cc\u0646\u06cc\u0688\u0627\u0688 \u0648 \u0679\u0648\u0628\u0627\u06af\u0648"
    ],
    "qs:gn_country":"TT",
    "qs:gn_fcode":"PPL",
    "qs:gn_pop":0,
    "qs:name":"La Brea",
    "qs:name_adm0":"Trinidad and Tobago",
    "qs:name_adm1":"Siparia",
    "qs:photos":214,
    "qs:photos_1k":43,
    "qs:photos_9k":1,
    "qs:photos_9r":4,
    "qs:photos_all":214,
    "qs:photos_sr":4,
    "qs:placetype":"Town",
    "qs:pop_sr":"0",
    "qs:woe_adm0":23424958,
    "wd:wordcount":759,
    "wof:name":"La Brea",
    "wof:placetype":"locality"
},
  "geometry": {"coordinates":[-61.61327,10.24234],"type":"Point"}
}