{
  "type": "Feature",
  "properties": {
    "gn:admin1_code":"TUP",
    "gn:asciiname":"Maturita",
    "gn:country_code":"TT",
    "gn:dem":62,
    "gn:feature_class":"P",
    "gn:feature_code":"PPL",
    "gn:name":"Maturita",
    "gn:population":0,
    "gn:timezone":"America/Port_of_Spain",
    "iso:country":"TT",
    "wof:name":"Maturita",
    "wof:placetype":"locality"
},
  "geometry": {"coordinates":[-61.26913,10.64152],"type":"Point"}
}