{
  "type": "Feature",
  "properties": {
    "gn:admin1_code":"03",
    "gn:asciiname":"Poole",
    "gn:country_code":"TT",
    "gn:dem":25,
    "gn:feature_class":"P",
    "gn:feature_code":"PPL",
    "gn:name":"Poole",
    "gn:population":0,
    "gn:timezone":"America/Port_of_Spain",
    "iso:country":"TT",
    "wof:name":"Poole",
    "wof:placetype":"locality"
},
  "geometry": {"coordinates":[-61.12355,10.4511],"type":"Point"}
}