{
  "type": "Feature",
  "properties": {
    "gn:admin1_code":"DMN",
    "gn:asciiname":"Dibe",
    "gn:country_code":"TT",
    "gn:dem":82,
    "gn:feature_class":"P",
    "gn:feature_code":"PPL",
    "gn:name":"Dibe",
    "gn:population":0,
    "gn:timezone":"America/Port_of_Spain",
    "iso:country":"TT",
    "wof:name":"Dibe",
    "wof:placetype":"locality"
},
  "geometry": {"coordinates":[-61.53117,10.68346],"type":"Point"}
}