{
  "type": "Feature",
  "properties": {
    "gn:admin1_code":"PRT",
    "gn:asciiname":"Sixth Company",
    "gn:country_code":"TT",
    "gn:dem":76,
    "gn:feature_class":"P",
    "gn:feature_code":"PPL",
    "gn:name":"Sixth Company",
    "gn:population":0,
    "gn:timezone":"America/Port_of_Spain",
    "iso:country":"TT",
    "name:und_x_variant":[
        "Sixth Company Village",
        "Sixth Company"
    ],
    "wof:name":"Sixth Company",
    "wof:placetype":"locality"
},
  "geometry": {"coordinates":[-61.34519,10.26259],"type":"Point"}
}