{
  "type": "Feature",
  "properties": {
    "gn:admin1_code":"TUP",
    "gn:asciiname":"Paradise",
    "gn:country_code":"TT",
    "gn:dem":77,
    "gn:feature_class":"P",
    "gn:feature_code":"PPL",
    "gn:name":"Paradise",
    "gn:population":15067,
    "gn:timezone":"America/Port_of_Spain",
    "iso:country":"TT",
    "wof:name":"Paradise",
    "wof:placetype":"locality",
    "wof:population":15067
},
  "geometry": {"coordinates":[-61.36298000000001,10.65298],"type":"Point"}
}