{
  "type": "Feature",
  "properties": {
    "gn:admin1_code":"11",
    "gn:asciiname":"Canaan",
    "gn:country_code":"TT",
    "gn:dem":12,
    "gn:feature_class":"P",
    "gn:feature_code":"PPL",
    "gn:name":"Canaan",
    "gn:population":0,
    "gn:timezone":"America/Port_of_Spain",
    "iso:country":"TT",
    "name:deu_x_preferred":[
        "Canaan"
    ],
    "name:pol_x_preferred":[
        "Canaan"
    ],
    "name:rus_x_preferred":[
        "\u041a\u0430\u043d\u0430\u0430\u043d"
    ],
    "wof:name":"Canaan",
    "wof:placetype":"locality"
},
  "geometry": {"coordinates":[-60.81259,11.16042],"type":"Point"}
}