{
  "type": "Feature",
  "properties": {
    "gn:admin1_code":"CTT",
    "gn:asciiname":"Brickfield",
    "gn:country_code":"TT",
    "gn:dem":5,
    "gn:feature_class":"P",
    "gn:feature_code":"PPL",
    "gn:name":"Brickfield",
    "gn:population":0,
    "gn:timezone":"America/Port_of_Spain",
    "iso:country":"TT",
    "wof:name":"Brickfield",
    "wof:placetype":"locality"
},
  "geometry": {"coordinates":[-61.46856,10.4902],"type":"Point"}
}