{
  "type": "Feature",
  "properties": {
    "gn:admin1_code":"11",
    "gn:asciiname":"The Whim",
    "gn:country_code":"TT",
    "gn:dem":137,
    "gn:feature_class":"P",
    "gn:feature_code":"PPL",
    "gn:name":"The Whim",
    "gn:population":0,
    "gn:timezone":"America/Port_of_Spain",
    "iso:country":"TT",
    "wof:name":"The Whim",
    "wof:placetype":"locality"
},
  "geometry": {"coordinates":[-60.74356,11.20629],"type":"Point"}
}