{
  "type": "Feature",
  "properties": {
    "gn:admin1_code":"SGE",
    "gn:asciiname":"Matura",
    "gn:country_code":"TT",
    "gn:dem":33,
    "gn:feature_class":"P",
    "gn:feature_code":"PPL",
    "gn:name":"Matura",
    "gn:population":0,
    "gn:timezone":"America/Port_of_Spain",
    "iso:country":"TT",
    "wof:name":"Matura",
    "wof:placetype":"locality"
},
  "geometry": {"coordinates":[-61.05897,10.67573],"type":"Point"}
}