{
  "type": "Feature",
  "properties": {
    "gn:admin1_code":"SGE",
    "gn:asciiname":"Matura",
    "gn:country_code":"TT",
    "gn:dem":33,
    "gn:feature_class":"P",
    "gn:feature_code":"PPL",
    "gn:name":"Matura",
    "gn:population":0,
    "gn:timezone":"America/Port_of_Spain",
    "iso:country":"TT",
    "name:bul_x_preferred":[
        "\u041c\u0430\u0442\u0443\u0440\u0430"
    ],
    "name:ces_x_preferred":[
        "Maturita"
    ],
    "name:deu_x_preferred":[
        "Matura"
    ],
    "name:fin_x_preferred":[
        "Matura"
    ],
    "name:fra_x_preferred":[
        "Maturit\u00e9"
    ],
    "name:hrv_x_preferred":[
        "Dr\u017eavna matura"
    ],
    "name:hun_x_preferred":[
        "\u00c9retts\u00e9gi vizsga"
    ],
    "name:ind_x_preferred":[
        "Matura"
    ],
    "name:lit_x_preferred":[
        "Brandos atestatas"
    ],
    "name:nor_x_preferred":[
        "Matura"
    ],
    "name:pol_x_preferred":[
        "Matura"
    ],
    "name:slk_x_preferred":[
        "Maturitn\u00e1 sk\u00fa\u0161ka"
    ],
    "name:slv_x_preferred":[
        "Matura"
    ],
    "name:sqi_x_preferred":[
        "Matura"
    ],
    "name:tur_x_preferred":[
        "Matura"
    ],
    "wof:name":"Matura",
    "wof:placetype":"locality"
},
  "geometry": {"coordinates":[-61.05897,10.67573],"type":"Point"}
}