{
  "type": "Feature",
  "properties": {
    "gn:country":"TT",
    "gn:fcode":"PPLA",
    "gn:pop":12281,
    "iso:country":"TT",
    "name:eng_x_preferred":[
        "Penal"
    ],
    "name:jpn_x_preferred":[
        "\u30da\u30ca\u30eb"
    ],
    "name:nld_x_preferred":[
        "Penal"
    ],
    "name:pol_x_preferred":[
        "Penal"
    ],
    "name:unk_x_variant":[
        "Pe\u00f1al Village"
    ],
    "name:urd_x_preferred":[
        "\u067e\u06cc\u0646\u0644\u060c \u0679\u0631\u06cc\u0646\u06cc\u0688\u0627\u0688 \u0648 \u0679\u0648\u0628\u0627\u06af\u0648"
    ],
    "qs:name":"Pe\u00f1al",
    "qs:photos_9r":0,
    "qs:photos_sr":0,
    "qs:pop_sr":"6",
    "wof:name":"Pe\u00f1al",
    "wof:placetype":"locality",
    "wof:population":12281
},
  "geometry": {"coordinates":[-61.46667,10.16667],"type":"Point"}
}