{
  "type": "Feature",
  "properties": {
    "gn:admin1_code":"SGE",
    "gn:asciiname":"Carmichael",
    "gn:country_code":"TT",
    "gn:dem":80,
    "gn:feature_class":"P",
    "gn:feature_code":"PPL",
    "gn:name":"Carmichael",
    "gn:population":0,
    "gn:timezone":"America/Port_of_Spain",
    "iso:country":"TT",
    "wof:name":"Carmichael",
    "wof:placetype":"locality"
},
  "geometry": {"coordinates":[-61.19798,10.49731],"type":"Point"}
}