{
  "type": "Feature",
  "properties": {
    "gn:admin1_code":"SGE",
    "gn:asciiname":"Carmichael",
    "gn:country_code":"TT",
    "gn:dem":80,
    "gn:feature_class":"P",
    "gn:feature_code":"PPL",
    "gn:name":"Carmichael",
    "gn:population":0,
    "gn:timezone":"America/Port_of_Spain",
    "iso:country":"TT",
    "name:ceb_x_preferred":[
        "Carmichael"
    ],
    "name:ces_x_preferred":[
        "Carmichael"
    ],
    "name:dan_x_preferred":[
        "Carmichael"
    ],
    "name:deu_x_preferred":[
        "Carmichael"
    ],
    "name:epo_x_preferred":[
        "Carmichael"
    ],
    "name:fra_x_preferred":[
        "Carmichael"
    ],
    "name:ita_x_preferred":[
        "Carmichael"
    ],
    "name:jpn_x_preferred":[
        "\u30ab\u30fc\u30de\u30a4\u30b1\u30eb"
    ],
    "name:nld_x_preferred":[
        "Carmichael"
    ],
    "name:rus_x_preferred":[
        "\u041a\u0430\u0440\u043c\u0430\u0439\u043a\u043b"
    ],
    "name:slv_x_preferred":[
        "Carmichael"
    ],
    "name:swe_x_preferred":[
        "Carmichael"
    ],
    "name:ukr_x_preferred":[
        "\u041a\u0430\u0440\u043c\u0430\u0439\u043a\u043b"
    ],
    "wof:name":"Carmichael",
    "wof:placetype":"locality"
},
  "geometry": {"coordinates":[-61.19798,10.49731],"type":"Point"}
}