{
  "type": "Feature",
  "properties": {
    "gn:admin1_code":"11",
    "gn:asciiname":"Arnos Vale",
    "gn:country_code":"TT",
    "gn:dem":104,
    "gn:feature_class":"P",
    "gn:feature_code":"PPL",
    "gn:name":"Arnos Vale",
    "gn:population":0,
    "gn:timezone":"America/Port_of_Spain",
    "iso:country":"TT",
    "wof:name":"Arnos Vale",
    "wof:placetype":"locality"
},
  "geometry": {"coordinates":[-60.75666999999999,11.20863],"type":"Point"}
}