{
  "type": "Feature",
  "properties": {
    "gn:admin1_code":"11",
    "gn:asciiname":"Plymouth",
    "gn:country_code":"TT",
    "gn:dem":13,
    "gn:feature_class":"P",
    "gn:feature_code":"PPL",
    "gn:name":"Plymouth",
    "gn:population":0,
    "gn:timezone":"America/Port_of_Spain",
    "iso:country":"TT",
    "wof:name":"Plymouth",
    "wof:placetype":"locality"
},
  "geometry": {"coordinates":[-60.76654,11.21621],"type":"Point"}
}