{
  "type": "Feature",
  "properties": {
    "gn:admin1_code":"CTT",
    "gn:asciiname":"Calcutta Settlement",
    "gn:country_code":"TT",
    "gn:dem":18,
    "gn:feature_class":"P",
    "gn:feature_code":"PPL",
    "gn:name":"Calcutta Settlement",
    "gn:population":0,
    "gn:timezone":"America/Port_of_Spain",
    "iso:country":"TT",
    "wof:name":"Calcutta Settlement",
    "wof:placetype":"locality"
},
  "geometry": {"coordinates":[-61.44881,10.4349],"type":"Point"}
}