{
  "type": "Feature",
  "properties": {
    "gn:admin1_code":"11",
    "gn:asciiname":"Tyson Hall",
    "gn:country_code":"TT",
    "gn:dem":15,
    "gn:feature_class":"P",
    "gn:feature_code":"PPL",
    "gn:name":"Tyson Hall",
    "gn:population":0,
    "gn:timezone":"America/Port_of_Spain",
    "iso:country":"TT",
    "wof:name":"Tyson Hall",
    "wof:placetype":"locality"
},
  "geometry": {"coordinates":[-60.80903000000001,11.15108],"type":"Point"}
}