{
  "type": "Feature",
  "properties": {
    "gn:admin1_code":"CTT",
    "gn:asciiname":"Brazil",
    "gn:country_code":"TT",
    "gn:dem":33,
    "gn:feature_class":"P",
    "gn:feature_code":"PPL",
    "gn:name":"Brazil",
    "gn:population":0,
    "gn:timezone":"America/Port_of_Spain",
    "iso:country":"TT",
    "wof:name":"Brazil",
    "wof:placetype":"locality"
},
  "geometry": {"coordinates":[-61.27569,10.55471],"type":"Point"}
}