{
  "type": "Feature",
  "properties": {
    "iso:country":"TT",
    "name:deu_x_preferred":[
        "Blanchisseuse"
    ],
    "name:dut_x_preferred":[
        "Blanchisseuse"
    ],
    "name:eng_x_preferred":[
        "Blanchisseuse"
    ],
    "name:fre_x_preferred":[
        "Blanchisseuse"
    ],
    "name:ger_x_preferred":[
        "Blanchisseuse"
    ],
    "name:jpn_x_preferred":[
        "\u30d6\u30e9\u30f3\u30c1\u30c3\u30bb\u30a6\u30bb"
    ],
    "name:spa_x_preferred":[
        "Blanchisseuse"
    ],
    "name:unk_x_variant":[
        "Blanchisseuse Village"
    ],
    "qs:gn_country":"TT",
    "qs:gn_fcode":"PPL",
    "qs:gn_pop":0,
    "qs:name":"Blanchisseuse",
    "qs:name_adm0":"Trinidad and Tobago",
    "qs:name_adm1":"Tanapuna-Piarco",
    "qs:photos":585,
    "qs:photos_1k":119,
    "qs:photos_9k":3,
    "qs:photos_9r":5,
    "qs:photos_all":585,
    "qs:photos_sr":8,
    "qs:placetype":"Town",
    "qs:pop_sr":"3",
    "qs:woe_adm0":23424958,
    "wd:wordcount":212,
    "wof:name":"Blanchisseuse",
    "wof:placetype":"locality"
},
  "geometry": {"coordinates":[-61.3048,10.79604],"type":"Point"}
}