{
  "type": "Feature",
  "properties": {
    "gn:admin1_code":"SGE",
    "gn:asciiname":"Ravin Anglais",
    "gn:country_code":"TT",
    "gn:dem":31,
    "gn:feature_class":"P",
    "gn:feature_code":"PPL",
    "gn:name":"Ravin Anglais",
    "gn:population":0,
    "gn:timezone":"America/Port_of_Spain",
    "iso:country":"TT",
    "wof:name":"Ravin Anglais",
    "wof:placetype":"locality"
},
  "geometry": {"coordinates":[-60.95338,10.79188],"type":"Point"}
}