{
  "type": "Feature",
  "properties": {
    "gn:admin1_code":"CTT",
    "gn:asciiname":"Caratal",
    "gn:country_code":"TT",
    "gn:dem":63,
    "gn:feature_class":"P",
    "gn:feature_code":"PPL",
    "gn:name":"Caratal",
    "gn:population":0,
    "gn:timezone":"America/Port_of_Spain",
    "iso:country":"TT",
    "wof:name":"Caratal",
    "wof:placetype":"locality"
},
  "geometry": {"coordinates":[-61.20876,10.52817],"type":"Point"}
}