{
  "type": "Feature",
  "properties": {
    "gn:admin1_code":"03",
    "gn:asciiname":"Plum Mitan",
    "gn:country_code":"TT",
    "gn:dem":34,
    "gn:feature_class":"P",
    "gn:feature_code":"PPL",
    "gn:name":"Plum Mitan",
    "gn:population":0,
    "gn:timezone":"America/Port_of_Spain",
    "iso:country":"TT",
    "name:und_x_variant":[
        "Plum Mitan Settlement",
        "Mitan",
        "Plum Mitan"
    ],
    "wof:name":"Plum Mitan",
    "wof:placetype":"locality"
},
  "geometry": {"coordinates":[-61.11666999999999,10.45],"type":"Point"}
}