{
  "type": "Feature",
  "properties": {
    "gn:admin1_code":"03",
    "gn:asciiname":"Mouville",
    "gn:country_code":"TT",
    "gn:dem":6,
    "gn:feature_class":"P",
    "gn:feature_code":"PPL",
    "gn:name":"Mouville",
    "gn:population":0,
    "gn:timezone":"America/Port_of_Spain",
    "iso:country":"TT",
    "wof:name":"Mouville",
    "wof:placetype":"locality"
},
  "geometry": {"coordinates":[-61.0008,10.15258],"type":"Point"}
}