{
  "type": "Feature",
  "properties": {
    "gn:admin1_code":"CTT",
    "gn:asciiname":"Soledad",
    "gn:country_code":"TT",
    "gn:dem":33,
    "gn:feature_class":"P",
    "gn:feature_code":"PPL",
    "gn:name":"Soledad",
    "gn:population":0,
    "gn:timezone":"America/Port_of_Spain",
    "iso:country":"TT",
    "wof:name":"Soledad",
    "wof:placetype":"locality"
},
  "geometry": {"coordinates":[-61.45196,10.35797],"type":"Point"}
}