{
  "type": "Feature",
  "properties": {
    "gn:admin1_code":"SGE",
    "gn:asciiname":"Upper Fishing Pond",
    "gn:country_code":"TT",
    "gn:dem":41,
    "gn:feature_class":"P",
    "gn:feature_code":"PPL",
    "gn:name":"Upper Fishing Pond",
    "gn:population":0,
    "gn:timezone":"America/Port_of_Spain",
    "iso:country":"TT",
    "wof:name":"Upper Fishing Pond",
    "wof:placetype":"locality"
},
  "geometry": {"coordinates":[-61.05501,10.5879],"type":"Point"}
}