{
  "type": "Feature",
  "properties": {
    "gn:admin1_code":"TUP",
    "gn:asciiname":"Saint Helena",
    "gn:country_code":"TT",
    "gn:dem":13,
    "gn:feature_class":"P",
    "gn:feature_code":"PPL",
    "gn:name":"Saint Helena",
    "gn:population":0,
    "gn:timezone":"America/Port_of_Spain",
    "iso:country":"TT",
    "wof:name":"Saint Helena",
    "wof:placetype":"locality"
},
  "geometry": {"coordinates":[-61.33645,10.57978],"type":"Point"}
}