{
  "type": "Feature",
  "properties": {
    "gn:admin1_code":"CTT",
    "gn:asciiname":"Madras Settlement",
    "gn:country_code":"TT",
    "gn:dem":39,
    "gn:feature_class":"P",
    "gn:feature_code":"PPL",
    "gn:name":"Madras Settlement",
    "gn:population":0,
    "gn:timezone":"America/Port_of_Spain",
    "iso:country":"TT",
    "wof:name":"Madras Settlement",
    "wof:placetype":"locality"
},
  "geometry": {"coordinates":[-61.3343,10.55344],"type":"Point"}
}