{
  "type": "Feature",
  "properties": {
    "gn:admin1_code":"01",
    "gn:asciiname":"Malabar Settlement",
    "gn:country_code":"TT",
    "gn:dem":53,
    "gn:feature_class":"P",
    "gn:feature_code":"PPL",
    "gn:name":"Malabar Settlement",
    "gn:population":0,
    "gn:timezone":"America/Port_of_Spain",
    "iso:country":"TT",
    "wof:name":"Malabar Settlement",
    "wof:placetype":"locality"
},
  "geometry": {"coordinates":[-61.2814,10.62531],"type":"Point"}
}