{
  "type": "Feature",
  "properties": {
    "gn:admin1_code":"PRT",
    "gn:asciiname":"Saint Julien",
    "gn:country_code":"TT",
    "gn:dem":71,
    "gn:feature_class":"P",
    "gn:feature_code":"PPL",
    "gn:name":"Saint Julien",
    "gn:population":0,
    "gn:timezone":"America/Port_of_Spain",
    "iso:country":"TT",
    "name:und_x_variant":[
        "Saint Julien Village",
        "Saint Julien"
    ],
    "wof:name":"Saint Julien",
    "wof:placetype":"locality"
},
  "geometry": {"coordinates":[-61.35884,10.27109],"type":"Point"}
}