{
  "type": "Feature",
  "properties": {
    "gn:admin1_code":"SJL",
    "gn:asciiname":"La Pastora",
    "gn:country_code":"TT",
    "gn:dem":120,
    "gn:feature_class":"P",
    "gn:feature_code":"PPL",
    "gn:name":"La Pastora",
    "gn:population":0,
    "gn:timezone":"America/Port_of_Spain",
    "iso:country":"TT",
    "wof:name":"La Pastora",
    "wof:placetype":"locality"
},
  "geometry": {"coordinates":[-61.46666999999999,10.71667],"type":"Point"}
}