{
  "type": "Feature",
  "properties": {
    "gn:admin1_code":"11",
    "gn:asciiname":"Studley Park",
    "gn:country_code":"TT",
    "gn:dem":50,
    "gn:feature_class":"P",
    "gn:feature_code":"PPL",
    "gn:name":"Studley Park",
    "gn:population":0,
    "gn:timezone":"America/Port_of_Spain",
    "iso:country":"TT",
    "wof:name":"Studley Park",
    "wof:placetype":"locality"
},
  "geometry": {"coordinates":[-60.66175,11.19772],"type":"Point"}
}