{
  "type": "Feature",
  "properties": {
    "gn:admin1_code":"CTT",
    "gn:asciiname":"Forres Park",
    "gn:country_code":"TT",
    "gn:dem":29,
    "gn:feature_class":"P",
    "gn:feature_code":"PPL",
    "gn:name":"Forres Park",
    "gn:population":0,
    "gn:timezone":"America/Port_of_Spain",
    "iso:country":"TT",
    "wof:name":"Forres Park",
    "wof:placetype":"locality"
},
  "geometry": {"coordinates":[-61.43131999999999,10.36365],"type":"Point"}
}