{
  "type": "Feature",
  "properties": {
    "gn:gn_country":"TT",
    "gn:gn_fcode":"PPL",
    "gn:gn_pop":56380,
    "gn:population":56380,
    "iso:country":"TT",
    "name:deu_x_preferred":[
        "Mon Repos"
    ],
    "name:est_x_preferred":[
        "Mon Repos"
    ],
    "name:fin_x_preferred":[
        "Mon Repos"
    ],
    "name:fra_x_preferred":[
        "Mon Repos"
    ],
    "name:nld_x_preferred":[
        "Mon Repos"
    ],
    "name:rus_x_preferred":[
        "\u041c\u043e\u043d-\u0420\u0435\u043f\u043e"
    ],
    "qs_pg:aaroncc":"TT",
    "qs_pg:gn_country":"TT",
    "qs_pg:gn_fcode":"PPL",
    "qs_pg:gn_pop":56380,
    "qs_pg:name":"Mon Repos",
    "qs_pg:photos_9r":0,
    "qs_pg:photos_sr":0,
    "qs_pg:pop_sr":8,
    "qs_pg:qs_pg_placetype":"locality",
    "wof:name":"Mon Repos",
    "wof:placetype":"locality",
    "wof:population":56380
},
  "geometry": {"coordinates":[-61.44605,10.283],"type":"Point"}
}