{
  "type": "Feature",
  "properties": {
    "gn:admin1_code":"PRT",
    "gn:asciiname":"Sainte Croix",
    "gn:country_code":"TT",
    "gn:dem":79,
    "gn:feature_class":"P",
    "gn:feature_code":"PPL",
    "gn:name":"Sainte Croix",
    "gn:population":0,
    "gn:timezone":"America/Port_of_Spain",
    "iso:country":"TT",
    "name:und_x_variant":[
        "Saint Croix",
        "Sainte Croix Village",
        "Sainte Croix"
    ],
    "wof:name":"Sainte Croix",
    "wof:placetype":"locality"
},
  "geometry": {"coordinates":[-61.36866,10.26291],"type":"Point"}
}