{
  "type": "Feature",
  "properties": {
    "gn:admin1_code":"11",
    "gn:asciiname":"Providence",
    "gn:country_code":"TT",
    "gn:dem":143,
    "gn:feature_class":"P",
    "gn:feature_code":"PPL",
    "gn:name":"Providence",
    "gn:population":0,
    "gn:timezone":"America/Port_of_Spain",
    "iso:country":"TT",
    "wof:name":"Providence",
    "wof:placetype":"locality"
},
  "geometry": {"coordinates":[-60.73389,11.20466],"type":"Point"}
}