{
  "type": "Feature",
  "properties": {
    "gn:admin1_code":"CHA",
    "gn:asciiname":"Chandernagore Settlement",
    "gn:country_code":"TT",
    "gn:dem":17,
    "gn:feature_class":"P",
    "gn:feature_code":"PPL",
    "gn:name":"Chandernagore Settlement",
    "gn:population":0,
    "gn:timezone":"America/Port_of_Spain",
    "iso:country":"TT",
    "wof:name":"Chandernagore Settlement",
    "wof:placetype":"locality"
},
  "geometry": {"coordinates":[-61.41021,10.49289],"type":"Point"}
}