{
  "type": "Feature",
  "properties": {
    "gn:admin1_code":"11",
    "gn:asciiname":"King's Bay",
    "gn:country_code":"TT",
    "gn:dem":164,
    "gn:feature_class":"P",
    "gn:feature_code":"PPL",
    "gn:name":"King\u2019s Bay",
    "gn:population":0,
    "gn:timezone":"America/Port_of_Spain",
    "iso:country":"TT",
    "wof:name":"King's Bay",
    "wof:placetype":"locality"
},
  "geometry": {"coordinates":[-60.55178000000001,11.27242],"type":"Point"}
}