{
  "type": "Feature",
  "properties": {
    "gn:admin1_code":"PRT",
    "gn:asciiname":"Lothian",
    "gn:country_code":"TT",
    "gn:dem":48,
    "gn:feature_class":"P",
    "gn:feature_code":"PPL",
    "gn:name":"Lothian",
    "gn:population":0,
    "gn:timezone":"America/Port_of_Spain",
    "iso:country":"TT",
    "name:und_x_variant":[
        "Lothians",
        "Lothian"
    ],
    "wof:name":"Lothian",
    "wof:placetype":"locality"
},
  "geometry": {"coordinates":[-61.38121999999999,10.25638],"type":"Point"}
}