{
  "type": "Feature",
  "properties": {
    "gn:admin1_code":"PRT",
    "gn:asciiname":"Lothian",
    "gn:country_code":"TT",
    "gn:dem":48,
    "gn:feature_class":"P",
    "gn:feature_code":"PPL",
    "gn:name":"Lothian",
    "gn:population":0,
    "gn:timezone":"America/Port_of_Spain",
    "iso:country":"TT",
    "name:ara_x_preferred":[
        "\u0644\u0648\u062b\u064a\u0627\u0646"
    ],
    "name:bel_x_preferred":[
        "\u041b\u043e\u0442\u044b\u044f\u043d"
    ],
    "name:bre_x_preferred":[
        "Lothian"
    ],
    "name:cym_x_preferred":[
        "Lothian"
    ],
    "name:deu_x_preferred":[
        "Lothian"
    ],
    "name:fin_x_preferred":[
        "Lothian"
    ],
    "name:fra_x_preferred":[
        "Lothian"
    ],
    "name:gla_x_preferred":[
        "Roinn Lodainn"
    ],
    "name:ita_x_preferred":[
        "Lothian"
    ],
    "name:jpn_x_preferred":[
        "\u30ed\u30fc\u30b8\u30a2\u30f3"
    ],
    "name:kaz_x_preferred":[
        "\u041b\u043e\u0442\u0438\u0430\u043d"
    ],
    "name:kor_x_preferred":[
        "\ub85c\ub514\uc5b8 \uc8fc"
    ],
    "name:lit_x_preferred":[
        "Lodianas"
    ],
    "name:nld_x_preferred":[
        "Lothian"
    ],
    "name:nor_x_preferred":[
        "Lothian"
    ],
    "name:pol_x_preferred":[
        "Lothian"
    ],
    "name:por_x_preferred":[
        "Lothian"
    ],
    "name:rus_x_preferred":[
        "\u041b\u043e\u0442\u0438\u0430\u043d"
    ],
    "name:sco_x_preferred":[
        "Lowden"
    ],
    "name:spa_x_preferred":[
        "Lothian"
    ],
    "name:srp_x_preferred":[
        "\u041b\u043e\u0442\u0438\u0458\u0430\u043d"
    ],
    "name:swe_x_preferred":[
        "Lothian"
    ],
    "name:ukr_x_preferred":[
        "\u041b\u043e\u0442\u0456\u0430\u043d"
    ],
    "name:und_x_variant":[
        "Lothians",
        "Lothian"
    ],
    "name:zho_x_preferred":[
        "\u6d1b\u932b\u5b89"
    ],
    "wof:name":"Lothian",
    "wof:placetype":"locality"
},
  "geometry": {"coordinates":[-61.38121999999999,10.25638],"type":"Point"}
}