{
  "type": "Feature",
  "properties": {
    "gn:admin1_code":"TUP",
    "gn:asciiname":"Piarco",
    "gn:country_code":"TT",
    "gn:dem":17,
    "gn:feature_class":"P",
    "gn:feature_code":"PPL",
    "gn:name":"Piarco",
    "gn:population":0,
    "gn:timezone":"America/Port_of_Spain",
    "iso:country":"TT",
    "name:und_x_variant":[
        "Piarco Savanna Village",
        "Piarco"
    ],
    "name:urd_x_preferred":[
        "\u067e\u06cc\u0627\u0631\u06a9\u0648"
    ],
    "wof:name":"Piarco",
    "wof:placetype":"locality"
},
  "geometry": {"coordinates":[-61.32488000000001,10.5881],"type":"Point"}
}