{
  "type": "Feature",
  "properties": {
    "gn:admin1_code":"05",
    "gn:asciiname":"Peru",
    "gn:country_code":"TT",
    "gn:dem":5,
    "gn:feature_class":"P",
    "gn:feature_code":"PPL",
    "gn:name":"Peru",
    "gn:population":0,
    "gn:timezone":"America/Port_of_Spain",
    "iso:country":"TT",
    "wof:name":"Peru",
    "wof:placetype":"locality"
},
  "geometry": {"coordinates":[-61.5358,10.66364],"type":"Point"}
}