{
  "type": "Feature",
  "properties": {
    "gn:admin1_code":"SIP",
    "gn:asciiname":"Pluck",
    "gn:country_code":"TT",
    "gn:dem":23,
    "gn:feature_class":"P",
    "gn:feature_code":"PPL",
    "gn:name":"Pluck",
    "gn:population":0,
    "gn:timezone":"America/Port_of_Spain",
    "iso:country":"TT",
    "wof:name":"Pluck",
    "wof:placetype":"locality"
},
  "geometry": {"coordinates":[-61.50361,10.17677],"type":"Point"}
}