{
  "type": "Feature",
  "properties": {
    "gn:admin1_code":"SGE",
    "gn:asciiname":"James Smart",
    "gn:country_code":"TT",
    "gn:dem":36,
    "gn:feature_class":"P",
    "gn:feature_code":"PPL",
    "gn:name":"James Smart",
    "gn:population":0,
    "gn:timezone":"America/Port_of_Spain",
    "iso:country":"TT",
    "name:und_x_variant":[
        "James Stewart",
        "James Smart"
    ],
    "wof:name":"James Smart",
    "wof:placetype":"locality"
},
  "geometry": {"coordinates":[-61.08333,10.55],"type":"Point"}
}