{
  "type": "Feature",
  "properties": {
    "iso:country":"TT",
    "name:deu_x_preferred":[
        "Tacarigua"
    ],
    "name:eng_x_preferred":[
        "Tacarigua"
    ],
    "name:fas_x_preferred":[
        "\u062a\u0627\u06a9\u0627\u0631\u06cc\u06af\u0648\u0622"
    ],
    "name:fra_x_preferred":[
        "Tacarigua"
    ],
    "name:ita_x_preferred":[
        "Tacarigua"
    ],
    "name:nld_x_preferred":[
        "Tacarigua"
    ],
    "name:pol_x_preferred":[
        "Tacarigua"
    ],
    "name:por_x_preferred":[
        "Tacarigua"
    ],
    "name:spa_x_preferred":[
        "Tacarigua"
    ],
    "name:zho_x_preferred":[
        "\u5854\u5361\u91cc\u74dc"
    ],
    "qs:gn_pop":0,
    "qs:name":"Tacarigua",
    "qs:name_adm0":"Trinidad and Tobago",
    "qs:name_adm1":"Tanapuna-Piarco",
    "qs:photos":262,
    "qs:photos_1k":53,
    "qs:photos_9k":1,
    "qs:photos_9r":4,
    "qs:photos_all":262,
    "qs:photos_sr":5,
    "qs:placetype":"Town",
    "qs:pop_sr":"0",
    "qs:woe_adm0":23424958,
    "wd:wordcount":88,
    "wof:name":"Tacarigua",
    "wof:placetype":"locality"
},
  "geometry": {"coordinates":[-61.37392,10.651919],"type":"Point"}
}