{
  "type": "Feature",
  "properties": {
    "gn:admin1_code":"PED",
    "gn:asciiname":"Duncan",
    "gn:country_code":"TT",
    "gn:dem":22,
    "gn:feature_class":"P",
    "gn:feature_code":"PPL",
    "gn:name":"Duncan",
    "gn:population":0,
    "gn:timezone":"America/Port_of_Spain",
    "iso:country":"TT",
    "name:bel_x_preferred":[
        "\u0414\u0443\u043d\u043a\u0430\u043d"
    ],
    "name:ceb_x_preferred":[
        "Duncan"
    ],
    "name:ces_x_preferred":[
        "Duncan"
    ],
    "name:deu_x_preferred":[
        "Duncan"
    ],
    "name:fas_x_preferred":[
        "\u062f\u0627\u0646\u06a9\u0646"
    ],
    "name:fin_x_preferred":[
        "Duncan"
    ],
    "name:fra_x_preferred":[
        "Duncan"
    ],
    "name:heb_x_preferred":[
        "\u05d3\u05d0\u05e0\u05e7\u05df"
    ],
    "name:ita_x_preferred":[
        "Duncan"
    ],
    "name:jpn_x_preferred":[
        "\u30c0\u30f3\u30ab\u30f3"
    ],
    "name:lav_x_preferred":[
        "Dankans"
    ],
    "name:lit_x_preferred":[
        "Duncan"
    ],
    "name:nld_x_preferred":[
        "Duncan"
    ],
    "name:pol_x_preferred":[
        "Duncan"
    ],
    "name:por_x_preferred":[
        "Duncan"
    ],
    "name:rus_x_preferred":[
        "\u0414\u0443\u043d\u043a\u0430\u043d"
    ],
    "name:slv_x_preferred":[
        "Duncan"
    ],
    "name:spa_x_preferred":[
        "Duncan"
    ],
    "name:swe_x_preferred":[
        "Duncan"
    ],
    "name:vol_x_preferred":[
        "Duncan"
    ],
    "wof:name":"Duncan",
    "wof:placetype":"locality"
},
  "geometry": {"coordinates":[-61.46,10.25286],"type":"Point"}
}