{
  "type": "Feature",
  "properties": {
    "gn:admin1_code":"PED",
    "gn:asciiname":"Duncan",
    "gn:country_code":"TT",
    "gn:dem":22,
    "gn:feature_class":"P",
    "gn:feature_code":"PPL",
    "gn:name":"Duncan",
    "gn:population":0,
    "gn:timezone":"America/Port_of_Spain",
    "iso:country":"TT",
    "wof:name":"Duncan",
    "wof:placetype":"locality"
},
  "geometry": {"coordinates":[-61.46,10.25286],"type":"Point"}
}