{
  "type": "Feature",
  "properties": {
    "gn:admin1_code":"SJL",
    "gn:asciiname":"Febeau",
    "gn:country_code":"TT",
    "gn:dem":18,
    "gn:feature_class":"P",
    "gn:feature_code":"PPL",
    "gn:name":"F\u00e9beau",
    "gn:population":0,
    "gn:timezone":"America/Port_of_Spain",
    "iso:country":"TT",
    "wof:name":"Febeau",
    "wof:placetype":"locality"
},
  "geometry": {"coordinates":[-61.45,10.65],"type":"Point"}
}